Metadata-Version: 1.1
Name: zops.virtualenv
Version: 0.2.0
Summary: Manage virtualenv generation, using cache when possible.
Home-page: https://github.com/zerotk/zops.virtualenv
Author: Alexandre Andrade
Author-email: kaniabi@gmail.com
License: MIT license
Keywords: development environment,shell,operations
Platform: UNKNOWN
Classifier: Development Status :: 2 - Pre-Alpha
Classifier: Intended Audience :: Developers
Classifier: License :: OSI Approved :: MIT License
Classifier: Natural Language :: English
Classifier: Programming Language :: Python :: 2
Classifier: Programming Language :: Python :: 2.7
Classifier: Programming Language :: Python :: 3
Classifier: Programming Language :: Python :: 3.5
